kivymd_extensions/__init__.py
kivymd_extensions/example_extension/__init__.py
kivymd_extensions/example_extension/example_button.py
kivymd_extensions.example_extension-0.1.1.dist-info/LICENSE
kivymd_extensions.example_extension-0.1.1.dist-info/METADATA
kivymd_extensions.example_extension-0.1.1.dist-info/WHEEL
kivymd_extensions.example_extension-0.1.1.dist-info/top_level.txt
kivymd_extensions.example_extension-0.1.1.dist-info/RECORD
